aio_sanitana_eden/__init__.py
aio_sanitana_eden/const.py
aio_sanitana_eden/exceptions.py
aio_sanitana_eden/get_info.py
aio_sanitana_eden/protocols.py
aio_sanitana_eden/sanitana_eden.py
aio_sanitana_eden/test_poll_status.py
aio_sanitana_eden/test_sanitana_eden.py
aio_sanitana_eden-0.0.13.dist-info/METADATA
aio_sanitana_eden-0.0.13.dist-info/WHEEL
aio_sanitana_eden-0.0.13.dist-info/licenses/LICENSE
aio_sanitana_eden-0.0.13.dist-info/RECORD
