Metadata-Version: 2.4
Name: aio_sanitana_eden
Version: 0.0.13
Summary: Async package to control a Sanitana Eden steam shower
Project-URL: Homepage, https://github.com/jochenvg/aio_sanitana_eden
Project-URL: Issues, https://github.com/jochenvg/aio_sanitana_eden/issues
Author-email: Jochen Van Guyse <jochen@vanguyse.net>
License-File: LICENSE
Classifier: License :: OSI Approved :: Apache Software License
Classifier: Operating System :: OS Independent
Classifier: Programming Language :: Python :: 3
Requires-Python: >=3.11
